mppq/__init__.py
mppq/common.py
mppq/data.py
mppq/defs.py
mppq/ffi.py
mppq/logger.py
mppq/py.typed
mppq/quant.py
mppq/register.py
mppq/storage.py
mppq/api/__init__.py
mppq/api/extension.py
mppq/api/interface.py
mppq/api/types.py
mppq/csrc/export.cc
mppq/csrc/build/.gitignore
mppq/csrc/build/readme.md
mppq/csrc/cpu/hist_mse.cc
mppq/csrc/cpu/hist_mse.h
mppq/csrc/cuda/PPQ.h
mppq/csrc/cuda/common.cuh
mppq/csrc/cuda/common.h
mppq/csrc/cuda/floating.cu
mppq/csrc/cuda/floating.h
mppq/csrc/cuda/isotone.cc
mppq/csrc/cuda/isotone.h
mppq/csrc/cuda/linear.cu
mppq/csrc/cuda/linear.h
mppq/csrc/cuda/sort.cu
mppq/csrc/cuda/sort.h
mppq/csrc/cuda/test.cu
mppq/csrc/cuda/test.h
mppq/csrc/cuda/train.cu
mppq/csrc/cuda/train.h
mppq/dispatcher/__init__.py
mppq/dispatcher/aggressive.py
mppq/dispatcher/allin.py
mppq/dispatcher/base.py
mppq/dispatcher/conservative.py
mppq/dispatcher/perseus.py
mppq/dispatcher/pointwise.py
mppq/dispatcher/scope.py
mppq/executor/README.md
mppq/executor/__init__.py
mppq/executor/base.py
mppq/executor/torch.py
mppq/executor/op/__init__.py
mppq/executor/op/base.py
mppq/executor/op/default.py
mppq/frontend/__init__.py
mppq/frontend/base.py
mppq/frontend/onnx/__init__.py
mppq/frontend/onnx/onnx_exporter.py
mppq/frontend/onnx/onnx_parser.py
mppq/frontend/onnx/onnxruntime_exporter.py
mppq/frontend/onnx/openvino_exporter.py
mppq/ir/README.md
mppq/ir/__init__.py
mppq/ir/deploy.py
mppq/ir/morph.py
mppq/ir/search.py
mppq/ir/training.py
mppq/ir/base/__init__.py
mppq/ir/base/command.py
mppq/ir/base/graph.py
mppq/ir/base/opdef.py
mppq/ir/base/processor.py
mppq/ir/base/quantize.py
mppq/ir/socket/__init__.py
mppq/ir/socket/default.py
mppq/quantization/__init__.py
mppq/quantization/algorithm/__init__.py
mppq/quantization/algorithm/equalization.py
mppq/quantization/algorithm/experimental.py
mppq/quantization/algorithm/training.py
mppq/quantization/analyse/__init__.py
mppq/quantization/analyse/graphwise.py
mppq/quantization/analyse/layerwise.py
mppq-0.7.6.dist-info/licenses/LICENSE
mppq-0.7.6.dist-info/WHEEL
mppq-0.7.6.dist-info/METADATA
mppq-0.7.6.dist-info/RECORD
