Metadata-Version: 2.4
Name: mppq
Version: 0.7.6
Summary: PPQ is an offline quantization tools
Author-email: PPQ <dcp-ppq@sensetime.com>, Wenyi Tang <wenyitang@outlook.com>
Requires-Python: >=3.11
Classifier: License :: OSI Approved :: Apache Software License
Classifier: Operating System :: OS Independent
Classifier: Programming Language :: Python :: 3.11
Classifier: Programming Language :: Python :: 3.12
Classifier: Programming Language :: Python :: 3.13
License-File: LICENSE
Requires-Dist: colorlog
Requires-Dist: numpy
Requires-Dist: onnx
Requires-Dist: pooch
Requires-Dist: protobuf>=5,<6
Requires-Dist: tabulate
Requires-Dist: torch>=2.0.0
Requires-Dist: tqdm
Project-URL: Home, https://github.com/LoSealL/ppq
